thetagang/__init__.py
thetagang/config.py
thetagang/entry.py
thetagang/exchange_hours.py
thetagang/fmt.py
thetagang/ibkr.py
thetagang/log.py
thetagang/main.py
thetagang/options.py
thetagang/orders.py
thetagang/portfolio_manager.py
thetagang/test_buy_only_percent.py
thetagang/thetagang.py
thetagang/trades.py
thetagang/util.py
thetagang-1.16.1.dist-info/METADATA
thetagang-1.16.1.dist-info/WHEEL
thetagang-1.16.1.dist-info/entry_points.txt
thetagang-1.16.1.dist-info/licenses/COPYING
thetagang-1.16.1.dist-info/licenses/LICENSE
thetagang-1.16.1.dist-info/RECORD
