Metadata-Version: 2.4
Name: thetagang
Version: 1.16.1
Summary: ThetaGang is an IBKR bot for getting money
Project-URL: Bug Tracker, https://github.com/brndnmtthws/thetagang/issues
Project-URL: Documentation, https://github.com/brndnmtthws/thetagang/blob/master/README.md
Project-URL: GitHub, https://github.com/brndnmtthws/thetagang
Project-URL: Homepage, https://github.com/brndnmtthws/thetagang
Project-URL: Repository, https://github.com/brndnmtthws/thetagang.git
Author-email: Brenden Matthews <brenden@brndn.io>
License-Expression: AGPL-3.0-only
License-File: COPYING
License-File: LICENSE
Requires-Python: <3.14,>=3.10
Requires-Dist: annotated-types<0.8,>=0.7.0
Requires-Dist: click-log<0.5,>=0.4.0
Requires-Dist: click<9,>=8.1.3
Requires-Dist: exchange-calendars>=4.8
Requires-Dist: ib-async<3,>=2.0.1
Requires-Dist: more-itertools<11.0,>=9.1
Requires-Dist: numpy<3.0,>=1.26
Requires-Dist: polyfactory<3,>=2.18.1
Requires-Dist: pydantic<3,>=2.10.2
Requires-Dist: python-dateutil<3,>=2.8.1
Requires-Dist: pytimeparse<2,>=1.1.8
Requires-Dist: rich<15,>=13.7.0
Requires-Dist: schema<0.8,>=0.7.5
Requires-Dist: toml<0.11,>=0.10.2
